generic_binary_sharding/__init__.py
generic_binary_sharding/dcp_package_serialize.py
generic_binary_sharding/node_module_serialize.py
generic_binary_sharding/serialize.py
generic_binary_sharding/utils.py
generic_binary_sharding-0.1.5.dist-info/METADATA
generic_binary_sharding-0.1.5.dist-info/entry_points.txt
generic_binary_sharding-0.1.5.dist-info/WHEEL
generic_binary_sharding-0.1.5.dist-info/RECORD
