Metadata-Version: 2.1
Name: generic-binary-sharding
Version: 0.1.5
Summary: 
Author: Hamada Gasmallah
Author-email: hamada@distributive.network
Requires-Python: >=3.9,<4.0
Classifier: Programming Language :: Python :: 3
Classifier: Programming Language :: Python :: 3.9
Classifier: Programming Language :: Python :: 3.10
Classifier: Programming Language :: Python :: 3.11
